{
  "ComponentIndexes": {},
  "ControlUniqueGuids": {},
  "ControlUniqueIds": {
    "App": 1,
    "Form1": 5,
    "Host": 3,
    "Screen1": 4
  },
  "FunctionParamsInvariantScripts": {},
  "FunctionParamsInvariantScriptsOnInstances": {},
  "HeaderLastSavedDateTimeUTC": "11/14/2023 15:16:15",
  "IsLegacyComponentAllowGlobalScopeCase": false,
  "LocalConnectionIDReferences": {},
  "LocalDatabaseReferencesAsEmpty": false,
  "LocalResourceFileNames": {},
  "LocalResourceRootPaths": {},
  "OrderComponentMetadata": {},
  "OrderComponentTemplate": {},
  "OrderDataSource": {
    "Accounts": 37,
    "Accounts\\account_accountcategorycode": 14,
    "Accounts\\account_accountclassificationcode": 15,
    "Accounts\\account_accountratingcode": 16,
    "Accounts\\account_address1_addresstypecode": 17,
    "Accounts\\account_address1_freighttermscode": 18,
    "Accounts\\account_address1_shippingmethodcode": 19,
    "Accounts\\account_address2_addresstypecode": 20,
    "Accounts\\account_address2_freighttermscode": 21,
    "Accounts\\account_address2_shippingmethodcode": 22,
    "Accounts\\account_businesstypecode": 23,
    "Accounts\\account_creditonhold": 0,
    "Accounts\\account_customersizecode": 24,
    "Accounts\\account_customertypecode": 25,
    "Accounts\\account_donotbulkemail": 1,
    "Accounts\\account_donotbulkpostalmail": 2,
    "Accounts\\account_donotemail": 3,
    "Accounts\\account_donotfax": 4,
    "Accounts\\account_donotphone": 5,
    "Accounts\\account_donotpostalmail": 6,
    "Accounts\\account_donotsendmm": 7,
    "Accounts\\account_followemail": 8,
    "Accounts\\account_industrycode": 26,
    "Accounts\\account_isprivate": 9,
    "Accounts\\account_marketingonly": 10,
    "Accounts\\account_merged": 11,
    "Accounts\\account_ownershipcode": 27,
    "Accounts\\account_participatesinworkflow": 13,
    "Accounts\\account_paymenttermscode": 28,
    "Accounts\\account_preferredappointmentdaycode": 29,
    "Accounts\\account_preferredappointmenttimecode": 30,
    "Accounts\\account_preferredcontactmethodcode": 31,
    "Accounts\\account_shippingmethodcode": 32,
    "Accounts\\account_statecode": 34,
    "Accounts\\account_statuscode": 35,
    "Accounts\\account_territorycode": 33,
    "Accounts\\default.cds_account_views": 36,
    "Accounts\\msdyn_account_msdyn_gdproptout": 12
  },
  "OrderGroupControls": {},
  "OrderPcfTemplate": {},
  "OrderTemplate": {},
  "OrderXMLTemplate": {
    "form": 0
  },
  "OverridablePropertiesEntry": {
    "App": {},
    "Form1": {},
    "Host": {},
    "Screen1": {}
  },
  "PCFDynamicSchemaForIRRetrievalEntry": {},
  "PCFTemplateEntry": {},
  "PublishOrderIndices": {
    "App": 0,
    "Form1": 0,
    "Host": 0,
    "Screen1": 0
  },
  "ResourcesJsonIndices": {},
  "RuleScreenIdWithoutScreen": {},
  "TemplateVersions": {},
  "VolatileProperties": {
    "AnalysisLoadTime": 0.019750899999999998,
    "ControlCount": {}
  },
  "WasLocalDatabaseReferencesEmpty": false
}